keywordsai_tracing/__init__.py
keywordsai_tracing/constants/__init__.py
keywordsai_tracing/constants/context_constants.py
keywordsai_tracing/constants/generic_constants.py
keywordsai_tracing/constants/keywordsai_config.py
keywordsai_tracing/constants/tracing.py
keywordsai_tracing/contexts/span.py
keywordsai_tracing/contexts/stdio.py
keywordsai_tracing/core/__init__.py
keywordsai_tracing/core/client.py
keywordsai_tracing/core/tracer.py
keywordsai_tracing/decorators/__init__.py
keywordsai_tracing/decorators/base.py
keywordsai_tracing/exporters/__init__.py
keywordsai_tracing/exporters/keywordsai.py
keywordsai_tracing/instruments.py
keywordsai_tracing/main.py
keywordsai_tracing/processors/__init__.py
keywordsai_tracing/processors/base.py
keywordsai_tracing/utils/__init__.py
keywordsai_tracing/utils/context.py
keywordsai_tracing/utils/imports.py
keywordsai_tracing/utils/instrumentation.py
keywordsai_tracing/utils/logging.py
keywordsai_tracing/utils/notebook.py
keywordsai_tracing/utils/preprocessing/__init__.py
keywordsai_tracing/utils/preprocessing/span_processing.py
keywordsai_tracing-0.0.59.dist-info/METADATA
keywordsai_tracing-0.0.59.dist-info/WHEEL
keywordsai_tracing-0.0.59.dist-info/RECORD
